litestar_oidc/__init__.py
litestar_oidc/auth.py
litestar_oidc/config.py
litestar_oidc/data.py
litestar_oidc/exceptions.py
litestar_oidc/handlers.py
litestar_oidc/middleware.py
litestar_oidc/plugin.py
litestar_oidc/providers.py
litestar_oidc/py.typed
litestar_oidc/routers.py
litestar_oidc/services.py
litestar_oidc-0.1.0.dist-info/METADATA
litestar_oidc-0.1.0.dist-info/WHEEL
litestar_oidc-0.1.0.dist-info/RECORD
