Metadata-Version: 2.4
Name: litestar-oidc
Version: 0.1.0
Summary: OIDC authentication for Litestar
Author-email: Niek Keijzer <hello@niekkeijzer.com>
Requires-Python: >=3.12
Requires-Dist: httpx>=0.28.1
Requires-Dist: litestar>=2.15.1
Requires-Dist: pyjwt>=2.10.1
